pipe/__init__.py
pipe/analyse.py
pipe/cent.py
pipe/fit_star_bg.py
pipe/level.py
pipe/make_multi_psf.py
pipe/multi_cent.py
pipe/multi_level.py
pipe/multi_psf.py
pipe/multi_satellites.py
pipe/multi_star.py
pipe/non_lin.py
pipe/optimal_params.py
pipe/pipe_control.py
pipe/pipe_log.py
pipe/pipe_param.py
pipe/pipe_statistics.py
pipe/psf.py
pipe/psf_library.py
pipe/psf_model.py
pipe/psf_phot.py
pipe/psf_worker.py
pipe/read.py
pipe/reduce.py
pipe/satellites.py
pipe/spline_pca.py
pipe/syntstar.py
pipe/version.py
pipe/config/__init__.py
pipe/config/pipeconf.py
pipe/data/CH_TU2020-02-18T06-15-13_REF_APP_GainCorrection_V0109.fits
pipe/data/README.rst
pipe/data/eigenlib_815_281_70_0.pkl
pipe/data/nonlin.txt
pipe/tests/__init__.py
pipe/tests/generate_fake_data.py
pipe/tests/test_reduce.py
pipe_cheops-1.1.dist-info/LICENSE.rst
pipe_cheops-1.1.dist-info/METADATA
pipe_cheops-1.1.dist-info/WHEEL
pipe_cheops-1.1.dist-info/top_level.txt
pipe_cheops-1.1.dist-info/RECORD
