Metadata-Version: 2.1
Name: pipe-cheops
Version: 1.1
Summary: PIPE is a package for extracting PSF photometry from CHEOPS data.
Home-page: https://github.com/alphapsa/PIPE
Author: Alexis Brandeker
Author-email: alexis@astro.su.se
License: GNU GPL v3+
Requires-Python: >=3.5
License-File: licenses/LICENSE.rst
Requires-Dist: numpy
Requires-Dist: scipy
Requires-Dist: astropy >=5.2
Requires-Dist: scikit-image
Provides-Extra: all
Requires-Dist: numpy ; extra == 'all'
Requires-Dist: scipy ; extra == 'all'
Requires-Dist: astropy >=5.2 ; extra == 'all'
Requires-Dist: scikit-image ; extra == 'all'
Provides-Extra: docs
Requires-Dist: sphinx ; extra == 'docs'
Requires-Dist: sphinx-automodapi ; extra == 'docs'
Requires-Dist: sphinx-astropy ; extra == 'docs'
Provides-Extra: test
Requires-Dist: pytest ; extra == 'test'
Requires-Dist: pytest-doctestplus ; extra == 'test'
Requires-Dist: pytest-cov ; extra == 'test'
Requires-Dist: pandas ; extra == 'test'
